{
  "a_comp_cor_00": {
    "CumulativeVarianceExplained": 0.047492338,
    "Mask": "combined",
    "Method": "aCompCor",
    "Retained": true,
    "SingularValue": 180.2510979019,
    "VarianceExplained": 0.047492338
  },
  "a_comp_cor_01": {
    "CumulativeVarianceExplained": 0.0768848467,
    "Mask": "combined",
    "Method": "aCompCor",
    "Retained": true,
    "SingularValue": 141.8026903954,
    "VarianceExplained": 0.0293925086
  },
  "a_comp_cor_02": {
    "CumulativeVarianceExplained": 0.1036388139,
    "Mask": "combined",
    "Method": "aCompCor",
    "Retained": true,
    "SingularValue": 135.2882999034,
    "VarianceExplained": 0.0267539673
  },
  "a_comp_cor_03": {
    "CumulativeVarianceExplained": 0.1242841504,
    "Mask": "combined",
    "Method": "aCompCor",
    "Retained": true,
    "SingularValue": 118.8439632782,
    "VarianceExplained": 0.0206453365
  },
  "a_comp_cor_04": {
    "CumulativeVarianceExplained": 0.1394729623,
    "Mask": "combined",
    "Method": "aCompCor",
    "Retained": true,
    "SingularValue": 101.9361071414,
    "VarianceExplained": 0.0151888118
  },
  "a_comp_cor_05": {
    "CumulativeVarianceExplained": 0.1539180858,
    "Mask": "combined",
    "Method": "aCompCor",
    "Retained": true,
    "SingularValue": 99.4092446148,
    "VarianceExplained": 0.0144451235
  },
  "a_comp_cor_06": {
    "CumulativeVarianceExplained": 0.166842781,
    "Mask": "combined",
    "Method": "aCompCor",
    "Retained": true,
    "SingularValue": 94.0321354695,
    "VarianceExplained": 0.0129246952
  },
  "a_comp_cor_07": {
    "CumulativeVarianceExplained": 0.1795314887,
    "Mask": "combined",
    "Method": "aCompCor",
    "Retained": true,
    "SingularValue": 93.1697304459,
    "VarianceExplained": 0.0126887076
  },
  "a_comp_cor_08": {
    "CumulativeVarianceExplained": 0.1920695027,
    "Mask": "combined",
    "Method": "aCompCor",
    "Retained": true,
    "SingularValue": 92.6148270682,
    "VarianceExplained": 0.0125380141
  },
  "a_comp_cor_09": {
    "CumulativeVarianceExplained": 0.2042791162,
    "Mask": "combined",
    "Method": "aCompCor",
    "Retained": true,
    "SingularValue": 91.3938769936,
    "VarianceExplained": 0.0122096134
  },
  "a_comp_cor_10": {
    "CumulativeVarianceExplained": 0.2159191899,
    "Mask": "combined",
    "Method": "aCompCor",
    "Retained": true,
    "SingularValue": 89.2368041459,
    "VarianceExplained": 0.0116400737
  },
  "a_comp_cor_11": {
    "CumulativeVarianceExplained": 0.2272973046,
    "Mask": "combined",
    "Method": "aCompCor",
    "Retained": true,
    "SingularValue": 88.2269565721,
    "VarianceExplained": 0.0113781148
  },
  "a_comp_cor_12": {
    "CumulativeVarianceExplained": 0.2384746264,
    "Mask": "combined",
    "Method": "aCompCor",
    "Retained": true,
    "SingularValue": 87.4450076981,
    "VarianceExplained": 0.0111773218
  },
  "a_comp_cor_13": {
    "CumulativeVarianceExplained": 0.2494789559,
    "Mask": "combined",
    "Method": "aCompCor",
    "Retained": true,
    "SingularValue": 86.7656722851,
    "VarianceExplained": 0.0110043295
  },
  "a_comp_cor_14": {
    "CumulativeVarianceExplained": 0.2602573852,
    "Mask": "combined",
    "Method": "aCompCor",
    "Retained": true,
    "SingularValue": 85.8704783793,
    "VarianceExplained": 0.0107784293
  },
  "a_comp_cor_15": {
    "CumulativeVarianceExplained": 0.2709141671,
    "Mask": "combined",
    "Method": "aCompCor",
    "Retained": true,
    "SingularValue": 85.3845281231,
    "VarianceExplained": 0.0106567819
  },
  "a_comp_cor_16": {
    "CumulativeVarianceExplained": 0.2812114276,
    "Mask": "combined",
    "Method": "aCompCor",
    "Retained": true,
    "SingularValue": 83.9318880543,
    "VarianceExplained": 0.0102972605
  },
  "a_comp_cor_17": {
    "CumulativeVarianceExplained": 0.2914609541,
    "Mask": "combined",
    "Method": "aCompCor",
    "Retained": true,
    "SingularValue": 83.737125052,
    "VarianceExplained": 0.0102495266
  },
  "a_comp_cor_18": {
    "CumulativeVarianceExplained": 0.301596063,
    "Mask": "combined",
    "Method": "aCompCor",
    "Retained": true,
    "SingularValue": 83.2684254623,
    "VarianceExplained": 0.0101351089
  },
  "a_comp_cor_19": {
    "CumulativeVarianceExplained": 0.3116497916,
    "Mask": "combined",
    "Method": "aCompCor",
    "Retained": true,
    "SingularValue": 82.9334481293,
    "VarianceExplained": 0.0100537286
  },
  "a_comp_cor_20": {
    "CumulativeVarianceExplained": 0.3215169911,
    "Mask": "combined",
    "Method": "aCompCor",
    "Retained": true,
    "SingularValue": 82.1605046375,
    "VarianceExplained": 0.0098671995
  },
  "a_comp_cor_21": {
    "CumulativeVarianceExplained": 0.3313307451,
    "Mask": "combined",
    "Method": "aCompCor",
    "Retained": true,
    "SingularValue": 81.937691842,
    "VarianceExplained": 0.0098137539
  },
  "a_comp_cor_22": {
    "CumulativeVarianceExplained": 0.3410907733,
    "Mask": "combined",
    "Method": "aCompCor",
    "Retained": true,
    "SingularValue": 81.7130989107,
    "VarianceExplained": 0.0097600283
  },
  "a_comp_cor_23": {
    "CumulativeVarianceExplained": 0.3507674524,
    "Mask": "combined",
    "Method": "aCompCor",
    "Retained": true,
    "SingularValue": 81.3634419265,
    "VarianceExplained": 0.0096766791
  },
  "a_comp_cor_24": {
    "CumulativeVarianceExplained": 0.3603334557,
    "Mask": "combined",
    "Method": "aCompCor",
    "Retained": true,
    "SingularValue": 80.8968119195,
    "VarianceExplained": 0.0095660033
  },
  "a_comp_cor_25": {
    "CumulativeVarianceExplained": 0.369865609,
    "Mask": "combined",
    "Method": "aCompCor",
    "Retained": true,
    "SingularValue": 80.7535552864,
    "VarianceExplained": 0.0095321533
  },
  "a_comp_cor_26": {
    "CumulativeVarianceExplained": 0.3792873981,
    "Mask": "combined",
    "Method": "aCompCor",
    "Retained": true,
    "SingularValue": 80.2847081011,
    "VarianceExplained": 0.0094217891
  },
  "a_comp_cor_27": {
    "CumulativeVarianceExplained": 0.3886246019,
    "Mask": "combined",
    "Method": "aCompCor",
    "Retained": true,
    "SingularValue": 79.9235125958,
    "VarianceExplained": 0.0093372038
  },
  "a_comp_cor_28": {
    "CumulativeVarianceExplained": 0.3979416024,
    "Mask": "combined",
    "Method": "aCompCor",
    "Retained": true,
    "SingularValue": 79.8369990152,
    "VarianceExplained": 0.0093170005
  },
  "a_comp_cor_29": {
    "CumulativeVarianceExplained": 0.4071661038,
    "Mask": "combined",
    "Method": "aCompCor",
    "Retained": true,
    "SingularValue": 79.4396996443,
    "VarianceExplained": 0.0092245014
  },
  "a_comp_cor_30": {
    "CumulativeVarianceExplained": 0.4162811369,
    "Mask": "combined",
    "Method": "aCompCor",
    "Retained": true,
    "SingularValue": 78.9669325508,
    "VarianceExplained": 0.0091150331
  },
  "a_comp_cor_31": {
    "CumulativeVarianceExplained": 0.4253339731,
    "Mask": "combined",
    "Method": "aCompCor",
    "Retained": true,
    "SingularValue": 78.6970540796,
    "VarianceExplained": 0.0090528362
  },
  "a_comp_cor_32": {
    "CumulativeVarianceExplained": 0.4343069302,
    "Mask": "combined",
    "Method": "aCompCor",
    "Retained": true,
    "SingularValue": 78.349086729,
    "VarianceExplained": 0.0089729571
  },
  "a_comp_cor_33": {
    "CumulativeVarianceExplained": 0.4431730148,
    "Mask": "combined",
    "Method": "aCompCor",
    "Retained": true,
    "SingularValue": 77.881100462,
    "VarianceExplained": 0.0088660846
  },
  "a_comp_cor_34": {
    "CumulativeVarianceExplained": 0.4519770533,
    "Mask": "combined",
    "Method": "aCompCor",
    "Retained": true,
    "SingularValue": 77.6081108014,
    "VarianceExplained": 0.0088040386
  },
  "a_comp_cor_35": {
    "CumulativeVarianceExplained": 0.4607391012,
    "Mask": "combined",
    "Method": "aCompCor",
    "Retained": true,
    "SingularValue": 77.4228142517,
    "VarianceExplained": 0.0087620478
  },
  "a_comp_cor_36": {
    "CumulativeVarianceExplained": 0.4694107912,
    "Mask": "combined",
    "Method": "aCompCor",
    "Retained": true,
    "SingularValue": 77.0225716515,
    "VarianceExplained": 0.00867169
  },
  "a_comp_cor_37": {
    "CumulativeVarianceExplained": 0.4780641484,
    "Mask": "combined",
    "Method": "aCompCor",
    "Retained": true,
    "SingularValue": 76.9411122262,
    "VarianceExplained": 0.0086533572
  },
  "a_comp_cor_38": {
    "CumulativeVarianceExplained": 0.486641018,
    "Mask": "combined",
    "Method": "aCompCor",
    "Retained": true,
    "SingularValue": 76.6003137026,
    "VarianceExplained": 0.0085768696
  },
  "a_comp_cor_39": {
    "CumulativeVarianceExplained": 0.4951782463,
    "Mask": "combined",
    "Method": "aCompCor",
    "Retained": true,
    "SingularValue": 76.4230895845,
    "VarianceExplained": 0.0085372283
  },
  "a_comp_cor_40": {
    "CumulativeVarianceExplained": 0.5036405284,
    "Mask": "combined",
    "Method": "aCompCor",
    "Retained": true,
    "SingularValue": 76.0869005966,
    "VarianceExplained": 0.0084622821
  },
  "c_comp_cor_00": {
    "CumulativeVarianceExplained": 0.0984615435,
    "Mask": "CSF",
    "Method": "aCompCor",
    "Retained": true,
    "SingularValue": 63.381629648,
    "VarianceExplained": 0.0984615435
  },
  "c_comp_cor_01": {
    "CumulativeVarianceExplained": 0.1733687558,
    "Mask": "CSF",
    "Method": "aCompCor",
    "Retained": true,
    "SingularValue": 55.2830377169,
    "VarianceExplained": 0.0749072122
  },
  "c_comp_cor_02": {
    "CumulativeVarianceExplained": 0.2361707202,
    "Mask": "CSF",
    "Method": "aCompCor",
    "Retained": true,
    "SingularValue": 50.6193653521,
    "VarianceExplained": 0.0628019644
  },
  "c_comp_cor_03": {
    "CumulativeVarianceExplained": 0.2908031147,
    "Mask": "CSF",
    "Method": "aCompCor",
    "Retained": true,
    "SingularValue": 47.2123044808,
    "VarianceExplained": 0.0546323945
  },
  "c_comp_cor_04": {
    "CumulativeVarianceExplained": 0.3406057681,
    "Mask": "CSF",
    "Method": "aCompCor",
    "Retained": true,
    "SingularValue": 45.0771367594,
    "VarianceExplained": 0.0498026534
  },
  "c_comp_cor_05": {
    "CumulativeVarianceExplained": 0.3797291881,
    "Mask": "CSF",
    "Method": "aCompCor",
    "Retained": true,
    "SingularValue": 39.9529165171,
    "VarianceExplained": 0.0391234201
  },
  "c_comp_cor_06": {
    "CumulativeVarianceExplained": 0.4124564965,
    "Mask": "CSF",
    "Method": "aCompCor",
    "Retained": true,
    "SingularValue": 36.5414036443,
    "VarianceExplained": 0.0327273083
  },
  "c_comp_cor_07": {
    "CumulativeVarianceExplained": 0.4397523435,
    "Mask": "CSF",
    "Method": "aCompCor",
    "Retained": true,
    "SingularValue": 33.3717029941,
    "VarianceExplained": 0.0272958471
  },
  "c_comp_cor_08": {
    "CumulativeVarianceExplained": 0.4649536854,
    "Mask": "CSF",
    "Method": "aCompCor",
    "Retained": true,
    "SingularValue": 32.0657877839,
    "VarianceExplained": 0.0252013418
  },
  "c_comp_cor_09": {
    "CumulativeVarianceExplained": 0.4883409773,
    "Mask": "CSF",
    "Method": "aCompCor",
    "Retained": true,
    "SingularValue": 30.8901523539,
    "VarianceExplained": 0.023387292
  },
  "c_comp_cor_10": {
    "CumulativeVarianceExplained": 0.5106445489,
    "Mask": "CSF",
    "Method": "aCompCor",
    "Retained": true,
    "SingularValue": 30.1659695847,
    "VarianceExplained": 0.0223035716
  },
  "dropped_0": {
    "CumulativeVarianceExplained": 0.407671668,
    "Mask": "Edge",
    "Method": "EdgeRegressor",
    "Retained": false,
    "SingularValue": 150.1258789254,
    "VarianceExplained": 0.0085740621
  },
  "dropped_1": {
    "CumulativeVarianceExplained": 0.416075649,
    "Mask": "Edge",
    "Method": "EdgeRegressor",
    "Retained": false,
    "SingularValue": 148.6294199078,
    "VarianceExplained": 0.008403981
  },
  "dropped_10": {
    "CumulativeVarianceExplained": 0.4875802472,
    "Mask": "Edge",
    "Method": "EdgeRegressor",
    "Retained": false,
    "SingularValue": 142.0069095201,
    "VarianceExplained": 0.0076717501
  },
  "dropped_11": {
    "CumulativeVarianceExplained": 0.4952489341,
    "Mask": "Edge",
    "Method": "EdgeRegressor",
    "Retained": false,
    "SingularValue": 141.9785554601,
    "VarianceExplained": 0.0076686868
  },
  "dropped_12": {
    "CumulativeVarianceExplained": 0.5028717561,
    "Mask": "Edge",
    "Method": "EdgeRegressor",
    "Retained": false,
    "SingularValue": 141.5533466415,
    "VarianceExplained": 0.007622822
  },
  "dropped_13": {
    "CumulativeVarianceExplained": 0.5103785958,
    "Mask": "Edge",
    "Method": "EdgeRegressor",
    "Retained": false,
    "SingularValue": 140.4723424827,
    "VarianceExplained": 0.0075068398
  },
  "dropped_14": {
    "CumulativeVarianceExplained": 0.5178572013,
    "Mask": "Edge",
    "Method": "EdgeRegressor",
    "Retained": false,
    "SingularValue": 140.2079255896,
    "VarianceExplained": 0.0074786055
  },
  "dropped_15": {
    "CumulativeVarianceExplained": 0.525308095,
    "Mask": "Edge",
    "Method": "EdgeRegressor",
    "Retained": false,
    "SingularValue": 139.9479160618,
    "VarianceExplained": 0.0074508937
  },
  "dropped_16": {
    "CumulativeVarianceExplained": 0.5326864447,
    "Mask": "Edge",
    "Method": "EdgeRegressor",
    "Retained": false,
    "SingularValue": 139.2649633143,
    "VarianceExplained": 0.0073783497
  },
  "dropped_17": {
    "CumulativeVarianceExplained": 0.540019332,
    "Mask": "Edge",
    "Method": "EdgeRegressor",
    "Retained": false,
    "SingularValue": 138.8352527361,
    "VarianceExplained": 0.0073328872
  },
  "dropped_18": {
    "CumulativeVarianceExplained": 0.5473248902,
    "Mask": "Edge",
    "Method": "EdgeRegressor",
    "Retained": false,
    "SingularValue": 138.5762983977,
    "VarianceExplained": 0.0073055583
  },
  "dropped_19": {
    "CumulativeVarianceExplained": 0.5546003309,
    "Mask": "Edge",
    "Method": "EdgeRegressor",
    "Retained": false,
    "SingularValue": 138.2903586895,
    "VarianceExplained": 0.0072754407
  },
  "dropped_2": {
    "CumulativeVarianceExplained": 0.4244134005,
    "Mask": "Edge",
    "Method": "EdgeRegressor",
    "Retained": false,
    "SingularValue": 148.0426079727,
    "VarianceExplained": 0.0083377516
  },
  "dropped_20": {
    "CumulativeVarianceExplained": 0.5618236062,
    "Mask": "Edge",
    "Method": "EdgeRegressor",
    "Retained": false,
    "SingularValue": 137.7936916121,
    "VarianceExplained": 0.0072232753
  },
  "dropped_21": {
    "CumulativeVarianceExplained": 0.5690206896,
    "Mask": "Edge",
    "Method": "EdgeRegressor",
    "Retained": false,
    "SingularValue": 137.5436421295,
    "VarianceExplained": 0.0071970834
  },
  "dropped_22": {
    "CumulativeVarianceExplained": 0.576118269,
    "Mask": "Edge",
    "Method": "EdgeRegressor",
    "Retained": false,
    "SingularValue": 136.5895204987,
    "VarianceExplained": 0.0070975794
  },
  "dropped_23": {
    "CumulativeVarianceExplained": 0.5831868639,
    "Mask": "Edge",
    "Method": "EdgeRegressor",
    "Retained": false,
    "SingularValue": 136.3103392776,
    "VarianceExplained": 0.0070685949
  },
  "dropped_24": {
    "CumulativeVarianceExplained": 0.5902387381,
    "Mask": "Edge",
    "Method": "EdgeRegressor",
    "Retained": false,
    "SingularValue": 136.1490228564,
    "VarianceExplained": 0.0070518742
  },
  "dropped_25": {
    "CumulativeVarianceExplained": 0.5972687015,
    "Mask": "Edge",
    "Method": "EdgeRegressor",
    "Retained": false,
    "SingularValue": 135.9373457461,
    "VarianceExplained": 0.0070299635
  },
  "dropped_26": {
    "CumulativeVarianceExplained": 0.6042894652,
    "Mask": "Edge",
    "Method": "EdgeRegressor",
    "Retained": false,
    "SingularValue": 135.8483688031,
    "VarianceExplained": 0.0070207636
  },
  "dropped_27": {
    "CumulativeVarianceExplained": 0.6112870326,
    "Mask": "Edge",
    "Method": "EdgeRegressor",
    "Retained": false,
    "SingularValue": 135.6237657115,
    "VarianceExplained": 0.0069975675
  },
  "dropped_28": {
    "CumulativeVarianceExplained": 0.6182581779,
    "Mask": "Edge",
    "Method": "EdgeRegressor",
    "Retained": false,
    "SingularValue": 135.3674718308,
    "VarianceExplained": 0.0069711453
  },
  "dropped_29": {
    "CumulativeVarianceExplained": 0.625194722,
    "Mask": "Edge",
    "Method": "EdgeRegressor",
    "Retained": false,
    "SingularValue": 135.0311066831,
    "VarianceExplained": 0.0069365441
  },
  "dropped_3": {
    "CumulativeVarianceExplained": 0.4326016926,
    "Mask": "Edge",
    "Method": "EdgeRegressor",
    "Retained": false,
    "SingularValue": 146.7097290985,
    "VarianceExplained": 0.0081882921
  },
  "dropped_30": {
    "CumulativeVarianceExplained": 0.6320873461,
    "Mask": "Edge",
    "Method": "EdgeRegressor",
    "Retained": false,
    "SingularValue": 134.6029409036,
    "VarianceExplained": 0.0068926241
  },
  "dropped_31": {
    "CumulativeVarianceExplained": 0.6389420896,
    "Mask": "Edge",
    "Method": "EdgeRegressor",
    "Retained": false,
    "SingularValue": 134.2325547074,
    "VarianceExplained": 0.0068547435
  },
  "dropped_32": {
    "CumulativeVarianceExplained": 0.6457832692,
    "Mask": "Edge",
    "Method": "EdgeRegressor",
    "Retained": false,
    "SingularValue": 134.0996827881,
    "VarianceExplained": 0.0068411797
  },
  "dropped_33": {
    "CumulativeVarianceExplained": 0.6525941733,
    "Mask": "Edge",
    "Method": "EdgeRegressor",
    "Retained": false,
    "SingularValue": 133.8026249176,
    "VarianceExplained": 0.0068109041
  },
  "dropped_34": {
    "CumulativeVarianceExplained": 0.6593865993,
    "Mask": "Edge",
    "Method": "EdgeRegressor",
    "Retained": false,
    "SingularValue": 133.6209975921,
    "VarianceExplained": 0.006792426
  },
  "dropped_35": {
    "CumulativeVarianceExplained": 0.6661724246,
    "Mask": "Edge",
    "Method": "EdgeRegressor",
    "Retained": false,
    "SingularValue": 133.5560573629,
    "VarianceExplained": 0.0067858253
  },
  "dropped_36": {
    "CumulativeVarianceExplained": 0.6729419144,
    "Mask": "Edge",
    "Method": "EdgeRegressor",
    "Retained": false,
    "SingularValue": 133.3952052736,
    "VarianceExplained": 0.0067694898
  },
  "dropped_37": {
    "CumulativeVarianceExplained": 0.6796650129,
    "Mask": "Edge",
    "Method": "EdgeRegressor",
    "Retained": false,
    "SingularValue": 132.9373411803,
    "VarianceExplained": 0.0067230985
  },
  "dropped_38": {
    "CumulativeVarianceExplained": 0.6863696066,
    "Mask": "Edge",
    "Method": "EdgeRegressor",
    "Retained": false,
    "SingularValue": 132.7542655204,
    "VarianceExplained": 0.0067045937
  },
  "dropped_39": {
    "CumulativeVarianceExplained": 0.6930386549,
    "Mask": "Edge",
    "Method": "EdgeRegressor",
    "Retained": false,
    "SingularValue": 132.4018899479,
    "VarianceExplained": 0.0066690483
  },
  "dropped_4": {
    "CumulativeVarianceExplained": 0.4407113175,
    "Mask": "Edge",
    "Method": "EdgeRegressor",
    "Retained": false,
    "SingularValue": 146.0032874213,
    "VarianceExplained": 0.0081096249
  },
  "dropped_40": {
    "CumulativeVarianceExplained": 0.6996882522,
    "Mask": "Edge",
    "Method": "EdgeRegressor",
    "Retained": false,
    "SingularValue": 132.2086659343,
    "VarianceExplained": 0.0066495973
  },
  "dropped_41": {
    "CumulativeVarianceExplained": 0.7063198507,
    "Mask": "Edge",
    "Method": "EdgeRegressor",
    "Retained": false,
    "SingularValue": 132.0296177282,
    "VarianceExplained": 0.0066315986
  },
  "dropped_42": {
    "CumulativeVarianceExplained": 0.7128980501,
    "Mask": "Edge",
    "Method": "EdgeRegressor",
    "Retained": false,
    "SingularValue": 131.4969762644,
    "VarianceExplained": 0.0065781993
  },
  "dropped_43": {
    "CumulativeVarianceExplained": 0.7194437392,
    "Mask": "Edge",
    "Method": "EdgeRegressor",
    "Retained": false,
    "SingularValue": 131.1716377297,
    "VarianceExplained": 0.0065456892
  },
  "dropped_44": {
    "CumulativeVarianceExplained": 0.7259810728,
    "Mask": "Edge",
    "Method": "EdgeRegressor",
    "Retained": false,
    "SingularValue": 131.0878907611,
    "VarianceExplained": 0.0065373336
  },
  "dropped_45": {
    "CumulativeVarianceExplained": 0.7325032389,
    "Mask": "Edge",
    "Method": "EdgeRegressor",
    "Retained": false,
    "SingularValue": 130.9357308775,
    "VarianceExplained": 0.006522166
  },
  "dropped_46": {
    "CumulativeVarianceExplained": 0.7390051327,
    "Mask": "Edge",
    "Method": "EdgeRegressor",
    "Retained": false,
    "SingularValue": 130.7320853575,
    "VarianceExplained": 0.0065018938
  },
  "dropped_47": {
    "CumulativeVarianceExplained": 0.7454950055,
    "Mask": "Edge",
    "Method": "EdgeRegressor",
    "Retained": false,
    "SingularValue": 130.611177569,
    "VarianceExplained": 0.0064898728
  },
  "dropped_48": {
    "CumulativeVarianceExplained": 0.7519641019,
    "Mask": "Edge",
    "Method": "EdgeRegressor",
    "Retained": false,
    "SingularValue": 130.4019426543,
    "VarianceExplained": 0.0064690963
  },
  "dropped_49": {
    "CumulativeVarianceExplained": 0.7583975907,
    "Mask": "Edge",
    "Method": "EdgeRegressor",
    "Retained": false,
    "SingularValue": 130.0425648627,
    "VarianceExplained": 0.0064334888
  },
  "dropped_5": {
    "CumulativeVarianceExplained": 0.4486328251,
    "Mask": "Edge",
    "Method": "EdgeRegressor",
    "Retained": false,
    "SingularValue": 144.299947632,
    "VarianceExplained": 0.0079215076
  },
  "dropped_50": {
    "CumulativeVarianceExplained": 0.7648075734,
    "Mask": "Edge",
    "Method": "EdgeRegressor",
    "Retained": false,
    "SingularValue": 129.8047781609,
    "VarianceExplained": 0.0064099827
  },
  "dropped_51": {
    "CumulativeVarianceExplained": 0.7712094918,
    "Mask": "Edge",
    "Method": "EdgeRegressor",
    "Retained": false,
    "SingularValue": 129.7231005287,
    "VarianceExplained": 0.0064019184
  },
  "dropped_52": {
    "CumulativeVarianceExplained": 0.7775660597,
    "Mask": "Edge",
    "Method": "EdgeRegressor",
    "Retained": false,
    "SingularValue": 129.2628114434,
    "VarianceExplained": 0.0063565679
  },
  "dropped_53": {
    "CumulativeVarianceExplained": 0.7839128096,
    "Mask": "Edge",
    "Method": "EdgeRegressor",
    "Retained": false,
    "SingularValue": 129.1629469419,
    "VarianceExplained": 0.0063467499
  },
  "dropped_54": {
    "CumulativeVarianceExplained": 0.7902412844,
    "Mask": "Edge",
    "Method": "EdgeRegressor",
    "Retained": false,
    "SingularValue": 128.9768532158,
    "VarianceExplained": 0.0063284747
  },
  "dropped_55": {
    "CumulativeVarianceExplained": 0.7965490659,
    "Mask": "Edge",
    "Method": "EdgeRegressor",
    "Retained": false,
    "SingularValue": 128.7658125747,
    "VarianceExplained": 0.0063077815
  },
  "dropped_56": {
    "CumulativeVarianceExplained": 0.8028498377,
    "Mask": "Edge",
    "Method": "EdgeRegressor",
    "Retained": false,
    "SingularValue": 128.6942459202,
    "VarianceExplained": 0.0063007719
  },
  "dropped_57": {
    "CumulativeVarianceExplained": 0.8091055526,
    "Mask": "Edge",
    "Method": "EdgeRegressor",
    "Retained": false,
    "SingularValue": 128.2332715572,
    "VarianceExplained": 0.0062557148
  },
  "dropped_58": {
    "CumulativeVarianceExplained": 0.8153397177,
    "Mask": "Edge",
    "Method": "EdgeRegressor",
    "Retained": false,
    "SingularValue": 128.0122124481,
    "VarianceExplained": 0.0062341652
  },
  "dropped_59": {
    "CumulativeVarianceExplained": 0.8215578064,
    "Mask": "Edge",
    "Method": "EdgeRegressor",
    "Retained": false,
    "SingularValue": 127.8470492245,
    "VarianceExplained": 0.0062180887
  },
  "dropped_6": {
    "CumulativeVarianceExplained": 0.4565278834,
    "Mask": "Edge",
    "Method": "EdgeRegressor",
    "Retained": false,
    "SingularValue": 144.0588432912,
    "VarianceExplained": 0.0078950583
  },
  "dropped_60": {
    "CumulativeVarianceExplained": 0.8277440866,
    "Mask": "Edge",
    "Method": "EdgeRegressor",
    "Retained": false,
    "SingularValue": 127.5196298108,
    "VarianceExplained": 0.0061862801
  },
  "dropped_61": {
    "CumulativeVarianceExplained": 0.8339149807,
    "Mask": "Edge",
    "Method": "EdgeRegressor",
    "Retained": false,
    "SingularValue": 127.3609527579,
    "VarianceExplained": 0.0061708941
  },
  "dropped_62": {
    "CumulativeVarianceExplained": 0.8400548643,
    "Mask": "Edge",
    "Method": "EdgeRegressor",
    "Retained": false,
    "SingularValue": 127.0405371929,
    "VarianceExplained": 0.0061398836
  },
  "dropped_63": {
    "CumulativeVarianceExplained": 0.8461842288,
    "Mask": "Edge",
    "Method": "EdgeRegressor",
    "Retained": false,
    "SingularValue": 126.9316641714,
    "VarianceExplained": 0.0061293644
  },
  "dropped_64": {
    "CumulativeVarianceExplained": 0.8522985242,
    "Mask": "Edge",
    "Method": "EdgeRegressor",
    "Retained": false,
    "SingularValue": 126.7755379229,
    "VarianceExplained": 0.0061142954
  },
  "dropped_65": {
    "CumulativeVarianceExplained": 0.8583840507,
    "Mask": "Edge",
    "Method": "EdgeRegressor",
    "Retained": false,
    "SingularValue": 126.4769349078,
    "VarianceExplained": 0.0060855265
  },
  "dropped_66": {
    "CumulativeVarianceExplained": 0.8644558019,
    "Mask": "Edge",
    "Method": "EdgeRegressor",
    "Retained": false,
    "SingularValue": 126.3337051673,
    "VarianceExplained": 0.0060717511
  },
  "dropped_67": {
    "CumulativeVarianceExplained": 0.870507516,
    "Mask": "Edge",
    "Method": "EdgeRegressor",
    "Retained": false,
    "SingularValue": 126.125080091,
    "VarianceExplained": 0.0060517142
  },
  "dropped_68": {
    "CumulativeVarianceExplained": 0.8765491172,
    "Mask": "Edge",
    "Method": "EdgeRegressor",
    "Retained": false,
    "SingularValue": 126.0196523564,
    "VarianceExplained": 0.0060416011
  },
  "dropped_69": {
    "CumulativeVarianceExplained": 0.8825616072,
    "Mask": "Edge",
    "Method": "EdgeRegressor",
    "Retained": false,
    "SingularValue": 125.715675787,
    "VarianceExplained": 0.00601249
  },
  "dropped_7": {
    "CumulativeVarianceExplained": 0.4643966164,
    "Mask": "Edge",
    "Method": "EdgeRegressor",
    "Retained": false,
    "SingularValue": 143.8184672871,
    "VarianceExplained": 0.007868733
  },
  "dropped_70": {
    "CumulativeVarianceExplained": 0.888549011,
    "Mask": "Edge",
    "Method": "EdgeRegressor",
    "Retained": false,
    "SingularValue": 125.4531371668,
    "VarianceExplained": 0.0059874038
  },
  "dropped_71": {
    "CumulativeVarianceExplained": 0.89452254,
    "Mask": "Edge",
    "Method": "EdgeRegressor",
    "Retained": false,
    "SingularValue": 125.3076951092,
    "VarianceExplained": 0.005973529
  },
  "dropped_72": {
    "CumulativeVarianceExplained": 0.9004743968,
    "Mask": "Edge",
    "Method": "EdgeRegressor",
    "Retained": false,
    "SingularValue": 125.08017689,
    "VarianceExplained": 0.0059518567
  },
  "dropped_73": {
    "CumulativeVarianceExplained": 0.9064017606,
    "Mask": "Edge",
    "Method": "EdgeRegressor",
    "Retained": false,
    "SingularValue": 124.8225489374,
    "VarianceExplained": 0.0059273639
  },
  "dropped_74": {
    "CumulativeVarianceExplained": 0.9123011303,
    "Mask": "Edge",
    "Method": "EdgeRegressor",
    "Retained": false,
    "SingularValue": 124.5274395268,
    "VarianceExplained": 0.0058993697
  },
  "dropped_75": {
    "CumulativeVarianceExplained": 0.9181615069,
    "Mask": "Edge",
    "Method": "EdgeRegressor",
    "Retained": false,
    "SingularValue": 124.1152116428,
    "VarianceExplained": 0.0058603765
  },
  "dropped_76": {
    "CumulativeVarianceExplained": 0.9240063121,
    "Mask": "Edge",
    "Method": "EdgeRegressor",
    "Retained": false,
    "SingularValue": 123.9502120929,
    "VarianceExplained": 0.0058448052
  },
  "dropped_77": {
    "CumulativeVarianceExplained": 0.9298186658,
    "Mask": "Edge",
    "Method": "EdgeRegressor",
    "Retained": false,
    "SingularValue": 123.6056348704,
    "VarianceExplained": 0.0058123537
  },
  "dropped_78": {
    "CumulativeVarianceExplained": 0.9356000992,
    "Mask": "Edge",
    "Method": "EdgeRegressor",
    "Retained": false,
    "SingularValue": 123.2764204509,
    "VarianceExplained": 0.0057814334
  },
  "dropped_79": {
    "CumulativeVarianceExplained": 0.9413703132,
    "Mask": "Edge",
    "Method": "EdgeRegressor",
    "Retained": false,
    "SingularValue": 123.156746755,
    "VarianceExplained": 0.0057702139
  },
  "dropped_8": {
    "CumulativeVarianceExplained": 0.4722204328,
    "Mask": "Edge",
    "Method": "EdgeRegressor",
    "Retained": false,
    "SingularValue": 143.4074043312,
    "VarianceExplained": 0.0078238163
  },
  "dropped_80": {
    "CumulativeVarianceExplained": 0.9470907493,
    "Mask": "Edge",
    "Method": "EdgeRegressor",
    "Retained": false,
    "SingularValue": 122.6243793861,
    "VarianceExplained": 0.0057204361
  },
  "dropped_81": {
    "CumulativeVarianceExplained": 0.9528097651,
    "Mask": "Edge",
    "Method": "EdgeRegressor",
    "Retained": false,
    "SingularValue": 122.6091555962,
    "VarianceExplained": 0.0057190158
  },
  "dropped_82": {
    "CumulativeVarianceExplained": 0.9585075841,
    "Mask": "Edge",
    "Method": "EdgeRegressor",
    "Retained": false,
    "SingularValue": 122.381725949,
    "VarianceExplained": 0.0056978189
  },
  "dropped_83": {
    "CumulativeVarianceExplained": 0.9641688079,
    "Mask": "Edge",
    "Method": "EdgeRegressor",
    "Retained": false,
    "SingularValue": 121.9880850313,
    "VarianceExplained": 0.0056612238
  },
  "dropped_84": {
    "CumulativeVarianceExplained": 0.9698076159,
    "Mask": "Edge",
    "Method": "EdgeRegressor",
    "Retained": false,
    "SingularValue": 121.7463384827,
    "VarianceExplained": 0.0056388081
  },
  "dropped_85": {
    "CumulativeVarianceExplained": 0.9754106842,
    "Mask": "Edge",
    "Method": "EdgeRegressor",
    "Retained": false,
    "SingularValue": 121.3598999754,
    "VarianceExplained": 0.0056030683
  },
  "dropped_86": {
    "CumulativeVarianceExplained": 0.980964516,
    "Mask": "Edge",
    "Method": "EdgeRegressor",
    "Retained": false,
    "SingularValue": 120.8255024944,
    "VarianceExplained": 0.0055538317
  },
  "dropped_87": {
    "CumulativeVarianceExplained": 0.9864526683,
    "Mask": "Edge",
    "Method": "EdgeRegressor",
    "Retained": false,
    "SingularValue": 120.1089391725,
    "VarianceExplained": 0.0054881524
  },
  "dropped_88": {
    "CumulativeVarianceExplained": 0.991833736,
    "Mask": "Edge",
    "Method": "EdgeRegressor",
    "Retained": false,
    "SingularValue": 118.9313854052,
    "VarianceExplained": 0.0053810677
  },
  "dropped_89": {
    "CumulativeVarianceExplained": 0.9964266369,
    "Mask": "Edge",
    "Method": "EdgeRegressor",
    "Retained": false,
    "SingularValue": 109.8767462573,
    "VarianceExplained": 0.0045929009
  },
  "dropped_9": {
    "CumulativeVarianceExplained": 0.4799084971,
    "Mask": "Edge",
    "Method": "EdgeRegressor",
    "Retained": false,
    "SingularValue": 142.1578204995,
    "VarianceExplained": 0.0076880643
  },
  "dropped_90": {
    "CumulativeVarianceExplained": 1.0,
    "Mask": "Edge",
    "Method": "EdgeRegressor",
    "Retained": false,
    "SingularValue": 96.9171928636,
    "VarianceExplained": 0.0035733631
  },
  "dropped_91": {
    "CumulativeVarianceExplained": 1.0,
    "Mask": "Edge",
    "Method": "EdgeRegressor",
    "Retained": false,
    "SingularValue": 0.0,
    "VarianceExplained": 0.0
  },
  "dropped_92": {
    "CumulativeVarianceExplained": 1.0,
    "Mask": "Edge",
    "Method": "EdgeRegressor",
    "Retained": false,
    "SingularValue": 0.0,
    "VarianceExplained": 0.0
  },
  "dropped_93": {
    "CumulativeVarianceExplained": 1.0,
    "Mask": "Edge",
    "Method": "EdgeRegressor",
    "Retained": false,
    "SingularValue": 0.0,
    "VarianceExplained": 0.0
  },
  "dropped_94": {
    "CumulativeVarianceExplained": 1.0,
    "Mask": "Edge",
    "Method": "EdgeRegressor",
    "Retained": false,
    "SingularValue": 0.0,
    "VarianceExplained": 0.0
  },
  "dropped_95": {
    "CumulativeVarianceExplained": 1.0,
    "Mask": "Edge",
    "Method": "EdgeRegressor",
    "Retained": false,
    "SingularValue": 0.0,
    "VarianceExplained": 0.0
  },
  "edge_comp_00": {
    "CumulativeVarianceExplained": 0.0846486266,
    "Mask": "Edge",
    "Method": "EdgeRegressor",
    "Retained": true,
    "SingularValue": 471.7068791051,
    "VarianceExplained": 0.0846486266
  },
  "edge_comp_01": {
    "CumulativeVarianceExplained": 0.1165721897,
    "Mask": "Edge",
    "Method": "EdgeRegressor",
    "Retained": true,
    "SingularValue": 289.6796128135,
    "VarianceExplained": 0.0319235631
  },
  "edge_comp_02": {
    "CumulativeVarianceExplained": 0.146454802,
    "Mask": "Edge",
    "Method": "EdgeRegressor",
    "Retained": true,
    "SingularValue": 280.2667205453,
    "VarianceExplained": 0.0298826123
  },
  "edge_comp_03": {
    "CumulativeVarianceExplained": 0.1682613566,
    "Mask": "Edge",
    "Method": "EdgeRegressor",
    "Retained": true,
    "SingularValue": 239.417437728,
    "VarianceExplained": 0.0218065546
  },
  "edge_comp_04": {
    "CumulativeVarianceExplained": 0.1888002034,
    "Mask": "Edge",
    "Method": "EdgeRegressor",
    "Retained": true,
    "SingularValue": 232.3540672443,
    "VarianceExplained": 0.0205388467
  },
  "edge_comp_05": {
    "CumulativeVarianceExplained": 0.2064147699,
    "Mask": "Edge",
    "Method": "EdgeRegressor",
    "Retained": true,
    "SingularValue": 215.1781808,
    "VarianceExplained": 0.0176145665
  },
  "edge_comp_06": {
    "CumulativeVarianceExplained": 0.2215760916,
    "Mask": "Edge",
    "Method": "EdgeRegressor",
    "Retained": true,
    "SingularValue": 199.6322877301,
    "VarianceExplained": 0.0151613217
  },
  "edge_comp_07": {
    "CumulativeVarianceExplained": 0.2357861913,
    "Mask": "Edge",
    "Method": "EdgeRegressor",
    "Retained": true,
    "SingularValue": 193.2683836742,
    "VarianceExplained": 0.0142100997
  },
  "edge_comp_08": {
    "CumulativeVarianceExplained": 0.2491120258,
    "Mask": "Edge",
    "Method": "EdgeRegressor",
    "Retained": true,
    "SingularValue": 187.158458076,
    "VarianceExplained": 0.0133258344
  },
  "edge_comp_09": {
    "CumulativeVarianceExplained": 0.2608774663,
    "Mask": "Edge",
    "Method": "EdgeRegressor",
    "Retained": true,
    "SingularValue": 175.859708521,
    "VarianceExplained": 0.0117654406
  },
  "edge_comp_10": {
    "CumulativeVarianceExplained": 0.2726053549,
    "Mask": "Edge",
    "Method": "EdgeRegressor",
    "Retained": true,
    "SingularValue": 175.5788367646,
    "VarianceExplained": 0.0117278886
  },
  "edge_comp_11": {
    "CumulativeVarianceExplained": 0.2838748571,
    "Mask": "Edge",
    "Method": "EdgeRegressor",
    "Retained": true,
    "SingularValue": 172.1133736541,
    "VarianceExplained": 0.0112695022
  },
  "edge_comp_12": {
    "CumulativeVarianceExplained": 0.2947241248,
    "Mask": "Edge",
    "Method": "EdgeRegressor",
    "Retained": true,
    "SingularValue": 168.8738731771,
    "VarianceExplained": 0.0108492677
  },
  "edge_comp_13": {
    "CumulativeVarianceExplained": 0.3054599714,
    "Mask": "Edge",
    "Method": "EdgeRegressor",
    "Retained": true,
    "SingularValue": 167.988828656,
    "VarianceExplained": 0.0107358467
  },
  "edge_comp_14": {
    "CumulativeVarianceExplained": 0.3157237485,
    "Mask": "Edge",
    "Method": "EdgeRegressor",
    "Retained": true,
    "SingularValue": 164.2539630403,
    "VarianceExplained": 0.0102637771
  },
  "edge_comp_15": {
    "CumulativeVarianceExplained": 0.3257295456,
    "Mask": "Edge",
    "Method": "EdgeRegressor",
    "Retained": true,
    "SingularValue": 162.1765654835,
    "VarianceExplained": 0.0100057972
  },
  "edge_comp_16": {
    "CumulativeVarianceExplained": 0.3355584411,
    "Mask": "Edge",
    "Method": "EdgeRegressor",
    "Retained": true,
    "SingularValue": 160.7365377686,
    "VarianceExplained": 0.0098288954
  },
  "edge_comp_17": {
    "CumulativeVarianceExplained": 0.3450156037,
    "Mask": "Edge",
    "Method": "EdgeRegressor",
    "Retained": true,
    "SingularValue": 157.6676813051,
    "VarianceExplained": 0.0094571626
  },
  "edge_comp_18": {
    "CumulativeVarianceExplained": 0.3543910741,
    "Mask": "Edge",
    "Method": "EdgeRegressor",
    "Retained": true,
    "SingularValue": 156.9852268096,
    "VarianceExplained": 0.0093754704
  },
  "edge_comp_19": {
    "CumulativeVarianceExplained": 0.3635776423,
    "Mask": "Edge",
    "Method": "EdgeRegressor",
    "Retained": true,
    "SingularValue": 155.3956664658,
    "VarianceExplained": 0.0091865682
  },
  "edge_comp_20": {
    "CumulativeVarianceExplained": 0.3726886659,
    "Mask": "Edge",
    "Method": "EdgeRegressor",
    "Retained": true,
    "SingularValue": 154.7554091809,
    "VarianceExplained": 0.0091110236
  },
  "edge_comp_21": {
    "CumulativeVarianceExplained": 0.3816866772,
    "Mask": "Edge",
    "Method": "EdgeRegressor",
    "Retained": true,
    "SingularValue": 153.7926283767,
    "VarianceExplained": 0.0089980113
  },
  "edge_comp_22": {
    "CumulativeVarianceExplained": 0.3904671485,
    "Mask": "Edge",
    "Method": "EdgeRegressor",
    "Retained": true,
    "SingularValue": 151.9221736357,
    "VarianceExplained": 0.0087804713
  },
  "edge_comp_23": {
    "CumulativeVarianceExplained": 0.3990976059,
    "Mask": "Edge",
    "Method": "EdgeRegressor",
    "Retained": true,
    "SingularValue": 150.6187911523,
    "VarianceExplained": 0.0086304574
  },
  "framewise_displacement": {
    "Units": "mm"
  },
  "rot_x": {
    "Description": "Rotation about left-right axis. Also known as \"pitch\".",
    "Units": "rad"
  },
  "rot_y": {
    "Description": "Rotation about anterior-posterior axis. Also known as \"roll\".",
    "Units": "rad"
  },
  "rot_z": {
    "Description": "Rotation about superior-inferior axis. Also known as \"yaw\".",
    "Units": "rad"
  },
  "t_comp_cor_00": {
    "CumulativeVarianceExplained": 0.3090165469,
    "Method": "tCompCor",
    "Retained": true,
    "SingularValue": 265.2953236052,
    "VarianceExplained": 0.3090165469
  },
  "t_comp_cor_01": {
    "CumulativeVarianceExplained": 0.3880991561,
    "Method": "tCompCor",
    "Retained": true,
    "SingularValue": 134.2082525944,
    "VarianceExplained": 0.0790826092
  },
  "t_comp_cor_02": {
    "CumulativeVarianceExplained": 0.4597943899,
    "Method": "tCompCor",
    "Retained": true,
    "SingularValue": 127.7861747423,
    "VarianceExplained": 0.0716952338
  },
  "t_comp_cor_03": {
    "CumulativeVarianceExplained": 0.5152617005,
    "Method": "tCompCor",
    "Retained": true,
    "SingularValue": 112.3976630114,
    "VarianceExplained": 0.0554673105
  },
  "trans_x": {
    "Description": "Translation along left-right axis.",
    "Units": "mm"
  },
  "trans_y": {
    "Description": "Translation along anterior-posterior axis.",
    "Units": "mm"
  },
  "trans_z": {
    "Description": "Translation along superior-inferior axis.",
    "Units": "mm"
  },
  "w_comp_cor_00": {
    "CumulativeVarianceExplained": 0.0449688008,
    "Mask": "WM",
    "Method": "aCompCor",
    "Retained": true,
    "SingularValue": 166.2516878063,
    "VarianceExplained": 0.0449688008
  },
  "w_comp_cor_01": {
    "CumulativeVarianceExplained": 0.073911311,
    "Mask": "WM",
    "Method": "aCompCor",
    "Retained": true,
    "SingularValue": 133.3762517177,
    "VarianceExplained": 0.0289425103
  },
  "w_comp_cor_02": {
    "CumulativeVarianceExplained": 0.1000722826,
    "Mask": "WM",
    "Method": "aCompCor",
    "Retained": true,
    "SingularValue": 126.8052820418,
    "VarianceExplained": 0.0261609716
  },
  "w_comp_cor_03": {
    "CumulativeVarianceExplained": 0.1188714418,
    "Mask": "WM",
    "Method": "aCompCor",
    "Retained": true,
    "SingularValue": 107.4928613623,
    "VarianceExplained": 0.0187991593
  },
  "w_comp_cor_04": {
    "CumulativeVarianceExplained": 0.1331144442,
    "Mask": "WM",
    "Method": "aCompCor",
    "Retained": true,
    "SingularValue": 93.5645175901,
    "VarianceExplained": 0.0142430023
  },
  "w_comp_cor_05": {
    "CumulativeVarianceExplained": 0.1465192846,
    "Mask": "WM",
    "Method": "aCompCor",
    "Retained": true,
    "SingularValue": 90.7697697725,
    "VarianceExplained": 0.0134048404
  },
  "w_comp_cor_06": {
    "CumulativeVarianceExplained": 0.159269567,
    "Mask": "WM",
    "Method": "aCompCor",
    "Retained": true,
    "SingularValue": 88.5258921025,
    "VarianceExplained": 0.0127502824
  },
  "w_comp_cor_07": {
    "CumulativeVarianceExplained": 0.1717490017,
    "Mask": "WM",
    "Method": "aCompCor",
    "Retained": true,
    "SingularValue": 87.5805899564,
    "VarianceExplained": 0.0124794347
  },
  "w_comp_cor_08": {
    "CumulativeVarianceExplained": 0.1838117799,
    "Mask": "WM",
    "Method": "aCompCor",
    "Retained": true,
    "SingularValue": 86.1061321727,
    "VarianceExplained": 0.0120627782
  },
  "w_comp_cor_09": {
    "CumulativeVarianceExplained": 0.1957455795,
    "Mask": "WM",
    "Method": "aCompCor",
    "Retained": true,
    "SingularValue": 85.6445596159,
    "VarianceExplained": 0.0119337996
  },
  "w_comp_cor_10": {
    "CumulativeVarianceExplained": 0.2074299541,
    "Mask": "WM",
    "Method": "aCompCor",
    "Retained": true,
    "SingularValue": 84.7448170567,
    "VarianceExplained": 0.0116843746
  },
  "w_comp_cor_11": {
    "CumulativeVarianceExplained": 0.2187123616,
    "Mask": "WM",
    "Method": "aCompCor",
    "Retained": true,
    "SingularValue": 83.2743595714,
    "VarianceExplained": 0.0112824075
  },
  "w_comp_cor_12": {
    "CumulativeVarianceExplained": 0.2298506961,
    "Mask": "WM",
    "Method": "aCompCor",
    "Retained": true,
    "SingularValue": 82.7409567497,
    "VarianceExplained": 0.0111383345
  },
  "w_comp_cor_13": {
    "CumulativeVarianceExplained": 0.240779986,
    "Mask": "WM",
    "Method": "aCompCor",
    "Retained": true,
    "SingularValue": 81.9608364679,
    "VarianceExplained": 0.0109292899
  },
  "w_comp_cor_14": {
    "CumulativeVarianceExplained": 0.2516705729,
    "Mask": "WM",
    "Method": "aCompCor",
    "Retained": true,
    "SingularValue": 81.8155873711,
    "VarianceExplained": 0.0108905869
  },
  "w_comp_cor_15": {
    "CumulativeVarianceExplained": 0.2623253453,
    "Mask": "WM",
    "Method": "aCompCor",
    "Retained": true,
    "SingularValue": 80.9249611143,
    "VarianceExplained": 0.0106547724
  },
  "w_comp_cor_16": {
    "CumulativeVarianceExplained": 0.2728117557,
    "Mask": "WM",
    "Method": "aCompCor",
    "Retained": true,
    "SingularValue": 80.2830446793,
    "VarianceExplained": 0.0104864104
  },
  "w_comp_cor_17": {
    "CumulativeVarianceExplained": 0.2831719435,
    "Mask": "WM",
    "Method": "aCompCor",
    "Retained": true,
    "SingularValue": 79.7984073588,
    "VarianceExplained": 0.0103601878
  },
  "w_comp_cor_18": {
    "CumulativeVarianceExplained": 0.2933213855,
    "Mask": "WM",
    "Method": "aCompCor",
    "Retained": true,
    "SingularValue": 78.9826122093,
    "VarianceExplained": 0.010149442
  },
  "w_comp_cor_19": {
    "CumulativeVarianceExplained": 0.303387423,
    "Mask": "WM",
    "Method": "aCompCor",
    "Retained": true,
    "SingularValue": 78.6574171879,
    "VarianceExplained": 0.0100660375
  },
  "w_comp_cor_20": {
    "CumulativeVarianceExplained": 0.3134320498,
    "Mask": "WM",
    "Method": "aCompCor",
    "Retained": true,
    "SingularValue": 78.573719915,
    "VarianceExplained": 0.0100446269
  },
  "w_comp_cor_21": {
    "CumulativeVarianceExplained": 0.323431754,
    "Mask": "WM",
    "Method": "aCompCor",
    "Retained": true,
    "SingularValue": 78.3978197745,
    "VarianceExplained": 0.0099997041
  },
  "w_comp_cor_22": {
    "CumulativeVarianceExplained": 0.3333257247,
    "Mask": "WM",
    "Method": "aCompCor",
    "Retained": true,
    "SingularValue": 77.9822427754,
    "VarianceExplained": 0.0098939708
  },
  "w_comp_cor_23": {
    "CumulativeVarianceExplained": 0.3430649957,
    "Mask": "WM",
    "Method": "aCompCor",
    "Retained": true,
    "SingularValue": 77.3701848511,
    "VarianceExplained": 0.009739271
  },
  "w_comp_cor_24": {
    "CumulativeVarianceExplained": 0.3527141049,
    "Mask": "WM",
    "Method": "aCompCor",
    "Retained": true,
    "SingularValue": 77.0112231465,
    "VarianceExplained": 0.0096491092
  },
  "w_comp_cor_25": {
    "CumulativeVarianceExplained": 0.3623051094,
    "Mask": "WM",
    "Method": "aCompCor",
    "Retained": true,
    "SingularValue": 76.7790008773,
    "VarianceExplained": 0.0095910045
  },
  "w_comp_cor_26": {
    "CumulativeVarianceExplained": 0.3718453111,
    "Mask": "WM",
    "Method": "aCompCor",
    "Retained": true,
    "SingularValue": 76.5753848769,
    "VarianceExplained": 0.0095402017
  },
  "w_comp_cor_27": {
    "CumulativeVarianceExplained": 0.3813399629,
    "Mask": "WM",
    "Method": "aCompCor",
    "Retained": true,
    "SingularValue": 76.3923608383,
    "VarianceExplained": 0.0094946518
  },
  "w_comp_cor_28": {
    "CumulativeVarianceExplained": 0.3907640757,
    "Mask": "WM",
    "Method": "aCompCor",
    "Retained": true,
    "SingularValue": 76.1080595625,
    "VarianceExplained": 0.0094241129
  },
  "w_comp_cor_29": {
    "CumulativeVarianceExplained": 0.4001008492,
    "Mask": "WM",
    "Method": "aCompCor",
    "Retained": true,
    "SingularValue": 75.7545673259,
    "VarianceExplained": 0.0093367735
  },
  "w_comp_cor_30": {
    "CumulativeVarianceExplained": 0.4093857205,
    "Mask": "WM",
    "Method": "aCompCor",
    "Retained": true,
    "SingularValue": 75.5437174544,
    "VarianceExplained": 0.0092848712
  },
  "w_comp_cor_31": {
    "CumulativeVarianceExplained": 0.4184957684,
    "Mask": "WM",
    "Method": "aCompCor",
    "Retained": true,
    "SingularValue": 74.8291376666,
    "VarianceExplained": 0.0091100479
  },
  "w_comp_cor_32": {
    "CumulativeVarianceExplained": 0.4275654504,
    "Mask": "WM",
    "Method": "aCompCor",
    "Retained": true,
    "SingularValue": 74.6631727092,
    "VarianceExplained": 0.009069682
  },
  "w_comp_cor_33": {
    "CumulativeVarianceExplained": 0.4365609846,
    "Mask": "WM",
    "Method": "aCompCor",
    "Retained": true,
    "SingularValue": 74.3573474307,
    "VarianceExplained": 0.0089955342
  },
  "w_comp_cor_34": {
    "CumulativeVarianceExplained": 0.4455187332,
    "Mask": "WM",
    "Method": "aCompCor",
    "Retained": true,
    "SingularValue": 74.2010150133,
    "VarianceExplained": 0.0089577486
  },
  "w_comp_cor_35": {
    "CumulativeVarianceExplained": 0.4544221739,
    "Mask": "WM",
    "Method": "aCompCor",
    "Retained": true,
    "SingularValue": 73.975744759,
    "VarianceExplained": 0.0089034407
  },
  "w_comp_cor_36": {
    "CumulativeVarianceExplained": 0.4632947836,
    "Mask": "WM",
    "Method": "aCompCor",
    "Retained": true,
    "SingularValue": 73.8475511056,
    "VarianceExplained": 0.0088726097
  },
  "w_comp_cor_37": {
    "CumulativeVarianceExplained": 0.4720562233,
    "Mask": "WM",
    "Method": "aCompCor",
    "Retained": true,
    "SingularValue": 73.3834537038,
    "VarianceExplained": 0.0087614397
  },
  "w_comp_cor_38": {
    "CumulativeVarianceExplained": 0.4807709983,
    "Mask": "WM",
    "Method": "aCompCor",
    "Retained": true,
    "SingularValue": 73.1877674915,
    "VarianceExplained": 0.008714775
  },
  "w_comp_cor_39": {
    "CumulativeVarianceExplained": 0.4894539771,
    "Mask": "WM",
    "Method": "aCompCor",
    "Retained": true,
    "SingularValue": 73.0541314945,
    "VarianceExplained": 0.0086829789
  },
  "w_comp_cor_40": {
    "CumulativeVarianceExplained": 0.4980576558,
    "Mask": "WM",
    "Method": "aCompCor",
    "Retained": true,
    "SingularValue": 72.7197705525,
    "VarianceExplained": 0.0086036786
  },
  "w_comp_cor_41": {
    "CumulativeVarianceExplained": 0.5066270312,
    "Mask": "WM",
    "Method": "aCompCor",
    "Retained": true,
    "SingularValue": 72.5746573704,
    "VarianceExplained": 0.0085693754
  }
}